[
  {
    "id": 650,
    "name": "chespin",
    "speciesName": "chespin",
    "types": [
      "grass"
    ],
    "sprite": "https://raw.githubusercontent.com/PokeAPI/sprites/master/sprites/pokemon/other/home/650.png",
    "shinySprite": "https://raw.githubusercontent.com/PokeAPI/sprites/master/sprites/pokemon/other/home/shiny/650.png",
    "femaleSprite": null,
    "femaleShinySprite": null,
    "generation": 6,
    "is_legendary": false,
    "is_mythical": false,
    "is_baby": false,
    "gender_rate": 1,
    "is_mega": false,
    "is_gmax": false,
    "is_paradox": false,
    "is_primal": false,
    "is_alternate_form": false,
    "is_sublegendary": false,
    "is_ultra_beast": false,
    "evolution_stage": 0,
    "is_fully_evolved": false
  },
  {
    "id": 651,
    "name": "quilladin",
    "speciesName": "quilladin",
    "types": [
      "grass"
    ],
    "sprite": "https://raw.githubusercontent.com/PokeAPI/sprites/master/sprites/pokemon/other/home/651.png",
    "shinySprite": "https://raw.githubusercontent.com/PokeAPI/sprites/master/sprites/pokemon/other/home/shiny/651.png",
    "femaleSprite": null,
    "femaleShinySprite": null,
    "generation": 6,
    "is_legendary": false,
    "is_mythical": false,
    "is_baby": false,
    "gender_rate": 1,
    "is_mega": false,
    "is_gmax": false,
    "is_paradox": false,
    "is_primal": false,
    "is_alternate_form": false,
    "is_sublegendary": false,
    "is_ultra_beast": false,
    "evolution_stage": 1,
    "is_fully_evolved": false
  },
  {
    "id": 652,
    "name": "chesnaught",
    "speciesName": "chesnaught",
    "types": [
      "grass",
      "fighting"
    ],
    "sprite": "https://raw.githubusercontent.com/PokeAPI/sprites/master/sprites/pokemon/other/home/652.png",
    "shinySprite": "https://raw.githubusercontent.com/PokeAPI/sprites/master/sprites/pokemon/other/home/shiny/652.png",
    "femaleSprite": null,
    "femaleShinySprite": null,
    "generation": 6,
    "is_legendary": false,
    "is_mythical": false,
    "is_baby": false,
    "gender_rate": 1,
    "is_mega": false,
    "is_gmax": false,
    "is_paradox": false,
    "is_primal": false,
    "is_alternate_form": false,
    "is_sublegendary": false,
    "is_ultra_beast": false,
    "evolution_stage": 2,
    "is_fully_evolved": true
  },
  {
    "id": 653,
    "name": "fennekin",
    "speciesName": "fennekin",
    "types": [
      "fire"
    ],
    "sprite": "https://raw.githubusercontent.com/PokeAPI/sprites/master/sprites/pokemon/other/home/653.png",
    "shinySprite": "https://raw.githubusercontent.com/PokeAPI/sprites/master/sprites/pokemon/other/home/shiny/653.png",
    "femaleSprite": null,
    "femaleShinySprite": null,
    "generation": 6,
    "is_legendary": false,
    "is_mythical": false,
    "is_baby": false,
    "gender_rate": 1,
    "is_mega": false,
    "is_gmax": false,
    "is_paradox": false,
    "is_primal": false,
    "is_alternate_form": false,
    "is_sublegendary": false,
    "is_ultra_beast": false,
    "evolution_stage": 0,
    "is_fully_evolved": false
  },
  {
    "id": 654,
    "name": "braixen",
    "speciesName": "braixen",
    "types": [
      "fire"
    ],
    "sprite": "https://raw.githubusercontent.com/PokeAPI/sprites/master/sprites/pokemon/other/home/654.png",
    "shinySprite": "https://raw.githubusercontent.com/PokeAPI/sprites/master/sprites/pokemon/other/home/shiny/654.png",
    "femaleSprite": null,
    "femaleShinySprite": null,
    "generation": 6,
    "is_legendary": false,
    "is_mythical": false,
    "is_baby": false,
    "gender_rate": 1,
    "is_mega": false,
    "is_gmax": false,
    "is_paradox": false,
    "is_primal": false,
    "is_alternate_form": false,
    "is_sublegendary": false,
    "is_ultra_beast": false,
    "evolution_stage": 1,
    "is_fully_evolved": false
  },
  {
    "id": 655,
    "name": "delphox",
    "speciesName": "delphox",
    "types": [
      "fire",
      "psychic"
    ],
    "sprite": "https://raw.githubusercontent.com/PokeAPI/sprites/master/sprites/pokemon/other/home/655.png",
    "shinySprite": "https://raw.githubusercontent.com/PokeAPI/sprites/master/sprites/pokemon/other/home/shiny/655.png",
    "femaleSprite": null,
    "femaleShinySprite": null,
    "generation": 6,
    "is_legendary": false,
    "is_mythical": false,
    "is_baby": false,
    "gender_rate": 1,
    "is_mega": false,
    "is_gmax": false,
    "is_paradox": false,
    "is_primal": false,
    "is_alternate_form": false,
    "is_sublegendary": false,
    "is_ultra_beast": false,
    "evolution_stage": 2,
    "is_fully_evolved": true
  },
  {
    "id": 656,
    "name": "froakie",
    "speciesName": "froakie",
    "types": [
      "water"
    ],
    "sprite": "https://raw.githubusercontent.com/PokeAPI/sprites/master/sprites/pokemon/other/home/656.png",
    "shinySprite": "https://raw.githubusercontent.com/PokeAPI/sprites/master/sprites/pokemon/other/home/shiny/656.png",
    "femaleSprite": null,
    "femaleShinySprite": null,
    "generation": 6,
    "is_legendary": false,
    "is_mythical": false,
    "is_baby": false,
    "gender_rate": 1,
    "is_mega": false,
    "is_gmax": false,
    "is_paradox": false,
    "is_primal": false,
    "is_alternate_form": false,
    "is_sublegendary": false,
    "is_ultra_beast": false,
    "evolution_stage": 0,
    "is_fully_evolved": false
  },
  {
    "id": 657,
    "name": "frogadier",
    "speciesName": "frogadier",
    "types": [
      "water"
    ],
    "sprite": "https://raw.githubusercontent.com/PokeAPI/sprites/master/sprites/pokemon/other/home/657.png",
    "shinySprite": "https://raw.githubusercontent.com/PokeAPI/sprites/master/sprites/pokemon/other/home/shiny/657.png",
    "femaleSprite": null,
    "femaleShinySprite": null,
    "generation": 6,
    "is_legendary": false,
    "is_mythical": false,
    "is_baby": false,
    "gender_rate": 1,
    "is_mega": false,
    "is_gmax": false,
    "is_paradox": false,
    "is_primal": false,
    "is_alternate_form": false,
    "is_sublegendary": false,
    "is_ultra_beast": false,
    "evolution_stage": 1,
    "is_fully_evolved": false
  },
  {
    "id": 658,
    "name": "greninja",
    "speciesName": "greninja",
    "types": [
      "water",
      "dark"
    ],
    "sprite": "https://raw.githubusercontent.com/PokeAPI/sprites/master/sprites/pokemon/other/home/658.png",
    "shinySprite": "https://raw.githubusercontent.com/PokeAPI/sprites/master/sprites/pokemon/other/home/shiny/658.png",
    "femaleSprite": null,
    "femaleShinySprite": null,
    "generation": 6,
    "is_legendary": false,
    "is_mythical": false,
    "is_baby": false,
    "gender_rate": 1,
    "is_mega": false,
    "is_gmax": false,
    "is_paradox": false,
    "is_primal": false,
    "is_alternate_form": false,
    "is_sublegendary": false,
    "is_ultra_beast": false,
    "evolution_stage": 2,
    "is_fully_evolved": true
  },
  {
    "id": 659,
    "name": "bunnelby",
    "speciesName": "bunnelby",
    "types": [
      "normal"
    ],
    "sprite": "https://raw.githubusercontent.com/PokeAPI/sprites/master/sprites/pokemon/other/home/659.png",
    "shinySprite": "https://raw.githubusercontent.com/PokeAPI/sprites/master/sprites/pokemon/other/home/shiny/659.png",
    "femaleSprite": null,
    "femaleShinySprite": null,
    "generation": 6,
    "is_legendary": false,
    "is_mythical": false,
    "is_baby": false,
    "gender_rate": 4,
    "is_mega": false,
    "is_gmax": false,
    "is_paradox": false,
    "is_primal": false,
    "is_alternate_form": false,
    "is_sublegendary": false,
    "is_ultra_beast": false,
    "evolution_stage": 0,
    "is_fully_evolved": false
  },
  {
    "id": 660,
    "name": "diggersby",
    "speciesName": "diggersby",
    "types": [
      "normal",
      "ground"
    ],
    "sprite": "https://raw.githubusercontent.com/PokeAPI/sprites/master/sprites/pokemon/other/home/660.png",
    "shinySprite": "https://raw.githubusercontent.com/PokeAPI/sprites/master/sprites/pokemon/other/home/shiny/660.png",
    "femaleSprite": null,
    "femaleShinySprite": null,
    "generation": 6,
    "is_legendary": false,
    "is_mythical": false,
    "is_baby": false,
    "gender_rate": 4,
    "is_mega": false,
    "is_gmax": false,
    "is_paradox": false,
    "is_primal": false,
    "is_alternate_form": false,
    "is_sublegendary": false,
    "is_ultra_beast": false,
    "evolution_stage": 1,
    "is_fully_evolved": true
  },
  {
    "id": 661,
    "name": "fletchling",
    "speciesName": "fletchling",
    "types": [
      "normal",
      "flying"
    ],
    "sprite": "https://raw.githubusercontent.com/PokeAPI/sprites/master/sprites/pokemon/other/home/661.png",
    "shinySprite": "https://raw.githubusercontent.com/PokeAPI/sprites/master/sprites/pokemon/other/home/shiny/661.png",
    "femaleSprite": null,
    "femaleShinySprite": null,
    "generation": 6,
    "is_legendary": false,
    "is_mythical": false,
    "is_baby": false,
    "gender_rate": 4,
    "is_mega": false,
    "is_gmax": false,
    "is_paradox": false,
    "is_primal": false,
    "is_alternate_form": false,
    "is_sublegendary": false,
    "is_ultra_beast": false,
    "evolution_stage": 0,
    "is_fully_evolved": false
  },
  {
    "id": 662,
    "name": "fletchinder",
    "speciesName": "fletchinder",
    "types": [
      "fire",
      "flying"
    ],
    "sprite": "https://raw.githubusercontent.com/PokeAPI/sprites/master/sprites/pokemon/other/home/662.png",
    "shinySprite": "https://raw.githubusercontent.com/PokeAPI/sprites/master/sprites/pokemon/other/home/shiny/662.png",
    "femaleSprite": null,
    "femaleShinySprite": null,
    "generation": 6,
    "is_legendary": false,
    "is_mythical": false,
    "is_baby": false,
    "gender_rate": 4,
    "is_mega": false,
    "is_gmax": false,
    "is_paradox": false,
    "is_primal": false,
    "is_alternate_form": false,
    "is_sublegendary": false,
    "is_ultra_beast": false,
    "evolution_stage": 1,
    "is_fully_evolved": false
  },
  {
    "id": 663,
    "name": "talonflame",
    "speciesName": "talonflame",
    "types": [
      "fire",
      "flying"
    ],
    "sprite": "https://raw.githubusercontent.com/PokeAPI/sprites/master/sprites/pokemon/other/home/663.png",
    "shinySprite": "https://raw.githubusercontent.com/PokeAPI/sprites/master/sprites/pokemon/other/home/shiny/663.png",
    "femaleSprite": null,
    "femaleShinySprite": null,
    "generation": 6,
    "is_legendary": false,
    "is_mythical": false,
    "is_baby": false,
    "gender_rate": 4,
    "is_mega": false,
    "is_gmax": false,
    "is_paradox": false,
    "is_primal": false,
    "is_alternate_form": false,
    "is_sublegendary": false,
    "is_ultra_beast": false,
    "evolution_stage": 2,
    "is_fully_evolved": true
  },
  {
    "id": 664,
    "name": "scatterbug",
    "speciesName": "scatterbug",
    "types": [
      "bug"
    ],
    "sprite": "https://raw.githubusercontent.com/PokeAPI/sprites/master/sprites/pokemon/other/home/664.png",
    "shinySprite": "https://raw.githubusercontent.com/PokeAPI/sprites/master/sprites/pokemon/other/home/shiny/664.png",
    "femaleSprite": null,
    "femaleShinySprite": null,
    "generation": 6,
    "is_legendary": false,
    "is_mythical": false,
    "is_baby": false,
    "gender_rate": 4,
    "is_mega": false,
    "is_gmax": false,
    "is_paradox": false,
    "is_primal": false,
    "is_alternate_form": false,
    "is_sublegendary": false,
    "is_ultra_beast": false,
    "evolution_stage": 0,
    "is_fully_evolved": false
  },
  {
    "id": 665,
    "name": "spewpa",
    "speciesName": "spewpa",
    "types": [
      "bug"
    ],
    "sprite": "https://raw.githubusercontent.com/PokeAPI/sprites/master/sprites/pokemon/other/home/665.png",
    "shinySprite": "https://raw.githubusercontent.com/PokeAPI/sprites/master/sprites/pokemon/other/home/shiny/665.png",
    "femaleSprite": null,
    "femaleShinySprite": null,
    "generation": 6,
    "is_legendary": false,
    "is_mythical": false,
    "is_baby": false,
    "gender_rate": 4,
    "is_mega": false,
    "is_gmax": false,
    "is_paradox": false,
    "is_primal": false,
    "is_alternate_form": false,
    "is_sublegendary": false,
    "is_ultra_beast": false,
    "evolution_stage": 1,
    "is_fully_evolved": false
  },
  {
    "id": 666,
    "name": "vivillon",
    "speciesName": "vivillon",
    "types": [
      "bug",
      "flying"
    ],
    "sprite": "https://raw.githubusercontent.com/PokeAPI/sprites/master/sprites/pokemon/other/home/666.png",
    "shinySprite": "https://raw.githubusercontent.com/PokeAPI/sprites/master/sprites/pokemon/other/home/shiny/666.png",
    "femaleSprite": null,
    "femaleShinySprite": null,
    "generation": 6,
    "is_legendary": false,
    "is_mythical": false,
    "is_baby": false,
    "gender_rate": 4,
    "is_mega": false,
    "is_gmax": false,
    "is_paradox": false,
    "is_primal": false,
    "is_alternate_form": false,
    "is_sublegendary": false,
    "is_ultra_beast": false,
    "evolution_stage": 2,
    "is_fully_evolved": true
  },
  {
    "id": 667,
    "name": "litleo",
    "speciesName": "litleo",
    "types": [
      "fire",
      "normal"
    ],
    "sprite": "https://raw.githubusercontent.com/PokeAPI/sprites/master/sprites/pokemon/other/home/667.png",
    "shinySprite": "https://raw.githubusercontent.com/PokeAPI/sprites/master/sprites/pokemon/other/home/shiny/667.png",
    "femaleSprite": null,
    "femaleShinySprite": null,
    "generation": 6,
    "is_legendary": false,
    "is_mythical": false,
    "is_baby": false,
    "gender_rate": 7,
    "is_mega": false,
    "is_gmax": false,
    "is_paradox": false,
    "is_primal": false,
    "is_alternate_form": false,
    "is_sublegendary": false,
    "is_ultra_beast": false,
    "evolution_stage": 0,
    "is_fully_evolved": false
  },
  {
    "id": 668,
    "name": "pyroar",
    "speciesName": "pyroar",
    "types": [
      "fire",
      "normal"
    ],
    "sprite": "https://raw.githubusercontent.com/PokeAPI/sprites/master/sprites/pokemon/other/home/668.png",
    "shinySprite": "https://raw.githubusercontent.com/PokeAPI/sprites/master/sprites/pokemon/other/home/shiny/668.png",
    "femaleSprite": "https://raw.githubusercontent.com/PokeAPI/sprites/master/sprites/pokemon/other/home/female/668.png",
    "femaleShinySprite": "https://raw.githubusercontent.com/PokeAPI/sprites/master/sprites/pokemon/other/home/shiny/female/668.png",
    "generation": 6,
    "is_legendary": false,
    "is_mythical": false,
    "is_baby": false,
    "gender_rate": 7,
    "is_mega": false,
    "is_gmax": false,
    "is_paradox": false,
    "is_primal": false,
    "is_alternate_form": false,
    "is_sublegendary": false,
    "is_ultra_beast": false,
    "evolution_stage": 1,
    "is_fully_evolved": true
  },
  {
    "id": 669,
    "name": "flabebe",
    "speciesName": "flabebe",
    "types": [
      "fairy"
    ],
    "sprite": "https://raw.githubusercontent.com/PokeAPI/sprites/master/sprites/pokemon/other/home/669.png",
    "shinySprite": "https://raw.githubusercontent.com/PokeAPI/sprites/master/sprites/pokemon/other/home/shiny/669.png",
    "femaleSprite": null,
    "femaleShinySprite": null,
    "generation": 6,
    "is_legendary": false,
    "is_mythical": false,
    "is_baby": false,
    "gender_rate": 8,
    "is_mega": false,
    "is_gmax": false,
    "is_paradox": false,
    "is_primal": false,
    "is_alternate_form": false,
    "is_sublegendary": false,
    "is_ultra_beast": false,
    "evolution_stage": 0,
    "is_fully_evolved": false
  },
  {
    "id": 670,
    "name": "floette",
    "speciesName": "floette",
    "types": [
      "fairy"
    ],
    "sprite": "https://raw.githubusercontent.com/PokeAPI/sprites/master/sprites/pokemon/other/home/670.png",
    "shinySprite": "https://raw.githubusercontent.com/PokeAPI/sprites/master/sprites/pokemon/other/home/shiny/670.png",
    "femaleSprite": null,
    "femaleShinySprite": null,
    "generation": 6,
    "is_legendary": false,
    "is_mythical": false,
    "is_baby": false,
    "gender_rate": 8,
    "is_mega": false,
    "is_gmax": false,
    "is_paradox": false,
    "is_primal": false,
    "is_alternate_form": false,
    "is_sublegendary": false,
    "is_ultra_beast": false,
    "evolution_stage": 1,
    "is_fully_evolved": false
  },
  {
    "id": 671,
    "name": "florges",
    "speciesName": "florges",
    "types": [
      "fairy"
    ],
    "sprite": "https://raw.githubusercontent.com/PokeAPI/sprites/master/sprites/pokemon/other/home/671.png",
    "shinySprite": "https://raw.githubusercontent.com/PokeAPI/sprites/master/sprites/pokemon/other/home/shiny/671.png",
    "femaleSprite": null,
    "femaleShinySprite": null,
    "generation": 6,
    "is_legendary": false,
    "is_mythical": false,
    "is_baby": false,
    "gender_rate": 8,
    "is_mega": false,
    "is_gmax": false,
    "is_paradox": false,
    "is_primal": false,
    "is_alternate_form": false,
    "is_sublegendary": false,
    "is_ultra_beast": false,
    "evolution_stage": 2,
    "is_fully_evolved": true
  },
  {
    "id": 672,
    "name": "skiddo",
    "speciesName": "skiddo",
    "types": [
      "grass"
    ],
    "sprite": "https://raw.githubusercontent.com/PokeAPI/sprites/master/sprites/pokemon/other/home/672.png",
    "shinySprite": "https://raw.githubusercontent.com/PokeAPI/sprites/master/sprites/pokemon/other/home/shiny/672.png",
    "femaleSprite": null,
    "femaleShinySprite": null,
    "generation": 6,
    "is_legendary": false,
    "is_mythical": false,
    "is_baby": false,
    "gender_rate": 4,
    "is_mega": false,
    "is_gmax": false,
    "is_paradox": false,
    "is_primal": false,
    "is_alternate_form": false,
    "is_sublegendary": false,
    "is_ultra_beast": false,
    "evolution_stage": 0,
    "is_fully_evolved": false
  },
  {
    "id": 673,
    "name": "gogoat",
    "speciesName": "gogoat",
    "types": [
      "grass"
    ],
    "sprite": "https://raw.githubusercontent.com/PokeAPI/sprites/master/sprites/pokemon/other/home/673.png",
    "shinySprite": "https://raw.githubusercontent.com/PokeAPI/sprites/master/sprites/pokemon/other/home/shiny/673.png",
    "femaleSprite": null,
    "femaleShinySprite": null,
    "generation": 6,
    "is_legendary": false,
    "is_mythical": false,
    "is_baby": false,
    "gender_rate": 4,
    "is_mega": false,
    "is_gmax": false,
    "is_paradox": false,
    "is_primal": false,
    "is_alternate_form": false,
    "is_sublegendary": false,
    "is_ultra_beast": false,
    "evolution_stage": 1,
    "is_fully_evolved": true
  },
  {
    "id": 674,
    "name": "pancham",
    "speciesName": "pancham",
    "types": [
      "fighting"
    ],
    "sprite": "https://raw.githubusercontent.com/PokeAPI/sprites/master/sprites/pokemon/other/home/674.png",
    "shinySprite": "https://raw.githubusercontent.com/PokeAPI/sprites/master/sprites/pokemon/other/home/shiny/674.png",
    "femaleSprite": null,
    "femaleShinySprite": null,
    "generation": 6,
    "is_legendary": false,
    "is_mythical": false,
    "is_baby": false,
    "gender_rate": 4,
    "is_mega": false,
    "is_gmax": false,
    "is_paradox": false,
    "is_primal": false,
    "is_alternate_form": false,
    "is_sublegendary": false,
    "is_ultra_beast": false,
    "evolution_stage": 0,
    "is_fully_evolved": false
  },
  {
    "id": 675,
    "name": "pangoro",
    "speciesName": "pangoro",
    "types": [
      "fighting",
      "dark"
    ],
    "sprite": "https://raw.githubusercontent.com/PokeAPI/sprites/master/sprites/pokemon/other/home/675.png",
    "shinySprite": "https://raw.githubusercontent.com/PokeAPI/sprites/master/sprites/pokemon/other/home/shiny/675.png",
    "femaleSprite": null,
    "femaleShinySprite": null,
    "generation": 6,
    "is_legendary": false,
    "is_mythical": false,
    "is_baby": false,
    "gender_rate": 4,
    "is_mega": false,
    "is_gmax": false,
    "is_paradox": false,
    "is_primal": false,
    "is_alternate_form": false,
    "is_sublegendary": false,
    "is_ultra_beast": false,
    "evolution_stage": 1,
    "is_fully_evolved": true
  },
  {
    "id": 676,
    "name": "furfrou",
    "speciesName": "furfrou",
    "types": [
      "normal"
    ],
    "sprite": "https://raw.githubusercontent.com/PokeAPI/sprites/master/sprites/pokemon/other/home/676.png",
    "shinySprite": "https://raw.githubusercontent.com/PokeAPI/sprites/master/sprites/pokemon/other/home/shiny/676.png",
    "femaleSprite": null,
    "femaleShinySprite": null,
    "generation": 6,
    "is_legendary": false,
    "is_mythical": false,
    "is_baby": false,
    "gender_rate": 4,
    "is_mega": false,
    "is_gmax": false,
    "is_paradox": false,
    "is_primal": false,
    "is_alternate_form": false,
    "is_sublegendary": false,
    "is_ultra_beast": false,
    "evolution_stage": 0,
    "is_fully_evolved": true
  },
  {
    "id": 677,
    "name": "espurr",
    "speciesName": "espurr",
    "types": [
      "psychic"
    ],
    "sprite": "https://raw.githubusercontent.com/PokeAPI/sprites/master/sprites/pokemon/other/home/677.png",
    "shinySprite": "https://raw.githubusercontent.com/PokeAPI/sprites/master/sprites/pokemon/other/home/shiny/677.png",
    "femaleSprite": null,
    "femaleShinySprite": null,
    "generation": 6,
    "is_legendary": false,
    "is_mythical": false,
    "is_baby": false,
    "gender_rate": 4,
    "is_mega": false,
    "is_gmax": false,
    "is_paradox": false,
    "is_primal": false,
    "is_alternate_form": false,
    "is_sublegendary": false,
    "is_ultra_beast": false,
    "evolution_stage": 0,
    "is_fully_evolved": false
  },
  {
    "id": 678,
    "name": "meowstic-male",
    "speciesName": "meowstic",
    "types": [
      "psychic"
    ],
    "sprite": "https://raw.githubusercontent.com/PokeAPI/sprites/master/sprites/pokemon/other/home/678.png",
    "shinySprite": "https://raw.githubusercontent.com/PokeAPI/sprites/master/sprites/pokemon/other/home/shiny/678.png",
    "femaleSprite": "https://raw.githubusercontent.com/PokeAPI/sprites/master/sprites/pokemon/female/678.png",
    "femaleShinySprite": "https://raw.githubusercontent.com/PokeAPI/sprites/master/sprites/pokemon/shiny/female/678.png",
    "generation": 6,
    "is_legendary": false,
    "is_mythical": false,
    "is_baby": false,
    "gender_rate": 4,
    "is_mega": false,
    "is_gmax": false,
    "is_paradox": false,
    "is_primal": false,
    "is_alternate_form": true,
    "is_sublegendary": false,
    "is_ultra_beast": false,
    "evolution_stage": 1,
    "is_fully_evolved": true
  },
  {
    "id": 679,
    "name": "honedge",
    "speciesName": "honedge",
    "types": [
      "steel",
      "ghost"
    ],
    "sprite": "https://raw.githubusercontent.com/PokeAPI/sprites/master/sprites/pokemon/other/home/679.png",
    "shinySprite": "https://raw.githubusercontent.com/PokeAPI/sprites/master/sprites/pokemon/other/home/shiny/679.png",
    "femaleSprite": null,
    "femaleShinySprite": null,
    "generation": 6,
    "is_legendary": false,
    "is_mythical": false,
    "is_baby": false,
    "gender_rate": 4,
    "is_mega": false,
    "is_gmax": false,
    "is_paradox": false,
    "is_primal": false,
    "is_alternate_form": false,
    "is_sublegendary": false,
    "is_ultra_beast": false,
    "evolution_stage": 0,
    "is_fully_evolved": false
  },
  {
    "id": 680,
    "name": "doublade",
    "speciesName": "doublade",
    "types": [
      "steel",
      "ghost"
    ],
    "sprite": "https://raw.githubusercontent.com/PokeAPI/sprites/master/sprites/pokemon/other/home/680.png",
    "shinySprite": "https://raw.githubusercontent.com/PokeAPI/sprites/master/sprites/pokemon/other/home/shiny/680.png",
    "femaleSprite": null,
    "femaleShinySprite": null,
    "generation": 6,
    "is_legendary": false,
    "is_mythical": false,
    "is_baby": false,
    "gender_rate": 4,
    "is_mega": false,
    "is_gmax": false,
    "is_paradox": false,
    "is_primal": false,
    "is_alternate_form": false,
    "is_sublegendary": false,
    "is_ultra_beast": false,
    "evolution_stage": 1,
    "is_fully_evolved": false
  },
  {
    "id": 681,
    "name": "aegislash-shield",
    "speciesName": "aegislash",
    "types": [
      "steel",
      "ghost"
    ],
    "sprite": "https://raw.githubusercontent.com/PokeAPI/sprites/master/sprites/pokemon/other/home/681.png",
    "shinySprite": "https://raw.githubusercontent.com/PokeAPI/sprites/master/sprites/pokemon/other/home/shiny/681.png",
    "femaleSprite": null,
    "femaleShinySprite": null,
    "generation": 6,
    "is_legendary": false,
    "is_mythical": false,
    "is_baby": false,
    "gender_rate": 4,
    "is_mega": false,
    "is_gmax": false,
    "is_paradox": false,
    "is_primal": false,
    "is_alternate_form": true,
    "is_sublegendary": false,
    "is_ultra_beast": false,
    "evolution_stage": 2,
    "is_fully_evolved": true
  },
  {
    "id": 682,
    "name": "spritzee",
    "speciesName": "spritzee",
    "types": [
      "fairy"
    ],
    "sprite": "https://raw.githubusercontent.com/PokeAPI/sprites/master/sprites/pokemon/other/home/682.png",
    "shinySprite": "https://raw.githubusercontent.com/PokeAPI/sprites/master/sprites/pokemon/other/home/shiny/682.png",
    "femaleSprite": null,
    "femaleShinySprite": null,
    "generation": 6,
    "is_legendary": false,
    "is_mythical": false,
    "is_baby": false,
    "gender_rate": 4,
    "is_mega": false,
    "is_gmax": false,
    "is_paradox": false,
    "is_primal": false,
    "is_alternate_form": false,
    "is_sublegendary": false,
    "is_ultra_beast": false,
    "evolution_stage": 0,
    "is_fully_evolved": false
  },
  {
    "id": 683,
    "name": "aromatisse",
    "speciesName": "aromatisse",
    "types": [
      "fairy"
    ],
    "sprite": "https://raw.githubusercontent.com/PokeAPI/sprites/master/sprites/pokemon/other/home/683.png",
    "shinySprite": "https://raw.githubusercontent.com/PokeAPI/sprites/master/sprites/pokemon/other/home/shiny/683.png",
    "femaleSprite": null,
    "femaleShinySprite": null,
    "generation": 6,
    "is_legendary": false,
    "is_mythical": false,
    "is_baby": false,
    "gender_rate": 4,
    "is_mega": false,
    "is_gmax": false,
    "is_paradox": false,
    "is_primal": false,
    "is_alternate_form": false,
    "is_sublegendary": false,
    "is_ultra_beast": false,
    "evolution_stage": 1,
    "is_fully_evolved": true
  },
  {
    "id": 684,
    "name": "swirlix",
    "speciesName": "swirlix",
    "types": [
      "fairy"
    ],
    "sprite": "https://raw.githubusercontent.com/PokeAPI/sprites/master/sprites/pokemon/other/home/684.png",
    "shinySprite": "https://raw.githubusercontent.com/PokeAPI/sprites/master/sprites/pokemon/other/home/shiny/684.png",
    "femaleSprite": null,
    "femaleShinySprite": null,
    "generation": 6,
    "is_legendary": false,
    "is_mythical": false,
    "is_baby": false,
    "gender_rate": 4,
    "is_mega": false,
    "is_gmax": false,
    "is_paradox": false,
    "is_primal": false,
    "is_alternate_form": false,
    "is_sublegendary": false,
    "is_ultra_beast": false,
    "evolution_stage": 0,
    "is_fully_evolved": false
  },
  {
    "id": 685,
    "name": "slurpuff",
    "speciesName": "slurpuff",
    "types": [
      "fairy"
    ],
    "sprite": "https://raw.githubusercontent.com/PokeAPI/sprites/master/sprites/pokemon/other/home/685.png",
    "shinySprite": "https://raw.githubusercontent.com/PokeAPI/sprites/master/sprites/pokemon/other/home/shiny/685.png",
    "femaleSprite": null,
    "femaleShinySprite": null,
    "generation": 6,
    "is_legendary": false,
    "is_mythical": false,
    "is_baby": false,
    "gender_rate": 4,
    "is_mega": false,
    "is_gmax": false,
    "is_paradox": false,
    "is_primal": false,
    "is_alternate_form": false,
    "is_sublegendary": false,
    "is_ultra_beast": false,
    "evolution_stage": 1,
    "is_fully_evolved": true
  },
  {
    "id": 686,
    "name": "inkay",
    "speciesName": "inkay",
    "types": [
      "dark",
      "psychic"
    ],
    "sprite": "https://raw.githubusercontent.com/PokeAPI/sprites/master/sprites/pokemon/other/home/686.png",
    "shinySprite": "https://raw.githubusercontent.com/PokeAPI/sprites/master/sprites/pokemon/other/home/shiny/686.png",
    "femaleSprite": null,
    "femaleShinySprite": null,
    "generation": 6,
    "is_legendary": false,
    "is_mythical": false,
    "is_baby": false,
    "gender_rate": 4,
    "is_mega": false,
    "is_gmax": false,
    "is_paradox": false,
    "is_primal": false,
    "is_alternate_form": false,
    "is_sublegendary": false,
    "is_ultra_beast": false,
    "evolution_stage": 0,
    "is_fully_evolved": false
  },
  {
    "id": 687,
    "name": "malamar",
    "speciesName": "malamar",
    "types": [
      "dark",
      "psychic"
    ],
    "sprite": "https://raw.githubusercontent.com/PokeAPI/sprites/master/sprites/pokemon/other/home/687.png",
    "shinySprite": "https://raw.githubusercontent.com/PokeAPI/sprites/master/sprites/pokemon/other/home/shiny/687.png",
    "femaleSprite": null,
    "femaleShinySprite": null,
    "generation": 6,
    "is_legendary": false,
    "is_mythical": false,
    "is_baby": false,
    "gender_rate": 4,
    "is_mega": false,
    "is_gmax": false,
    "is_paradox": false,
    "is_primal": false,
    "is_alternate_form": false,
    "is_sublegendary": false,
    "is_ultra_beast": false,
    "evolution_stage": 1,
    "is_fully_evolved": true
  },
  {
    "id": 688,
    "name": "binacle",
    "speciesName": "binacle",
    "types": [
      "rock",
      "water"
    ],
    "sprite": "https://raw.githubusercontent.com/PokeAPI/sprites/master/sprites/pokemon/other/home/688.png",
    "shinySprite": "https://raw.githubusercontent.com/PokeAPI/sprites/master/sprites/pokemon/other/home/shiny/688.png",
    "femaleSprite": null,
    "femaleShinySprite": null,
    "generation": 6,
    "is_legendary": false,
    "is_mythical": false,
    "is_baby": false,
    "gender_rate": 4,
    "is_mega": false,
    "is_gmax": false,
    "is_paradox": false,
    "is_primal": false,
    "is_alternate_form": false,
    "is_sublegendary": false,
    "is_ultra_beast": false,
    "evolution_stage": 0,
    "is_fully_evolved": false
  },
  {
    "id": 689,
    "name": "barbaracle",
    "speciesName": "barbaracle",
    "types": [
      "rock",
      "water"
    ],
    "sprite": "https://raw.githubusercontent.com/PokeAPI/sprites/master/sprites/pokemon/other/home/689.png",
    "shinySprite": "https://raw.githubusercontent.com/PokeAPI/sprites/master/sprites/pokemon/other/home/shiny/689.png",
    "femaleSprite": null,
    "femaleShinySprite": null,
    "generation": 6,
    "is_legendary": false,
    "is_mythical": false,
    "is_baby": false,
    "gender_rate": 4,
    "is_mega": false,
    "is_gmax": false,
    "is_paradox": false,
    "is_primal": false,
    "is_alternate_form": false,
    "is_sublegendary": false,
    "is_ultra_beast": false,
    "evolution_stage": 1,
    "is_fully_evolved": true
  },
  {
    "id": 690,
    "name": "skrelp",
    "speciesName": "skrelp",
    "types": [
      "poison",
      "water"
    ],
    "sprite": "https://raw.githubusercontent.com/PokeAPI/sprites/master/sprites/pokemon/other/home/690.png",
    "shinySprite": "https://raw.githubusercontent.com/PokeAPI/sprites/master/sprites/pokemon/other/home/shiny/690.png",
    "femaleSprite": null,
    "femaleShinySprite": null,
    "generation": 6,
    "is_legendary": false,
    "is_mythical": false,
    "is_baby": false,
    "gender_rate": 4,
    "is_mega": false,
    "is_gmax": false,
    "is_paradox": false,
    "is_primal": false,
    "is_alternate_form": false,
    "is_sublegendary": false,
    "is_ultra_beast": false,
    "evolution_stage": 0,
    "is_fully_evolved": false
  },
  {
    "id": 691,
    "name": "dragalge",
    "speciesName": "dragalge",
    "types": [
      "poison",
      "dragon"
    ],
    "sprite": "https://raw.githubusercontent.com/PokeAPI/sprites/master/sprites/pokemon/other/home/691.png",
    "shinySprite": "https://raw.githubusercontent.com/PokeAPI/sprites/master/sprites/pokemon/other/home/shiny/691.png",
    "femaleSprite": null,
    "femaleShinySprite": null,
    "generation": 6,
    "is_legendary": false,
    "is_mythical": false,
    "is_baby": false,
    "gender_rate": 4,
    "is_mega": false,
    "is_gmax": false,
    "is_paradox": false,
    "is_primal": false,
    "is_alternate_form": false,
    "is_sublegendary": false,
    "is_ultra_beast": false,
    "evolution_stage": 1,
    "is_fully_evolved": true
  },
  {
    "id": 692,
    "name": "clauncher",
    "speciesName": "clauncher",
    "types": [
      "water"
    ],
    "sprite": "https://raw.githubusercontent.com/PokeAPI/sprites/master/sprites/pokemon/other/home/692.png",
    "shinySprite": "https://raw.githubusercontent.com/PokeAPI/sprites/master/sprites/pokemon/other/home/shiny/692.png",
    "femaleSprite": null,
    "femaleShinySprite": null,
    "generation": 6,
    "is_legendary": false,
    "is_mythical": false,
    "is_baby": false,
    "gender_rate": 4,
    "is_mega": false,
    "is_gmax": false,
    "is_paradox": false,
    "is_primal": false,
    "is_alternate_form": false,
    "is_sublegendary": false,
    "is_ultra_beast": false,
    "evolution_stage": 0,
    "is_fully_evolved": false
  },
  {
    "id": 693,
    "name": "clawitzer",
    "speciesName": "clawitzer",
    "types": [
      "water"
    ],
    "sprite": "https://raw.githubusercontent.com/PokeAPI/sprites/master/sprites/pokemon/other/home/693.png",
    "shinySprite": "https://raw.githubusercontent.com/PokeAPI/sprites/master/sprites/pokemon/other/home/shiny/693.png",
    "femaleSprite": null,
    "femaleShinySprite": null,
    "generation": 6,
    "is_legendary": false,
    "is_mythical": false,
    "is_baby": false,
    "gender_rate": 4,
    "is_mega": false,
    "is_gmax": false,
    "is_paradox": false,
    "is_primal": false,
    "is_alternate_form": false,
    "is_sublegendary": false,
    "is_ultra_beast": false,
    "evolution_stage": 1,
    "is_fully_evolved": true
  },
  {
    "id": 694,
    "name": "helioptile",
    "speciesName": "helioptile",
    "types": [
      "electric",
      "normal"
    ],
    "sprite": "https://raw.githubusercontent.com/PokeAPI/sprites/master/sprites/pokemon/other/home/694.png",
    "shinySprite": "https://raw.githubusercontent.com/PokeAPI/sprites/master/sprites/pokemon/other/home/shiny/694.png",
    "femaleSprite": null,
    "femaleShinySprite": null,
    "generation": 6,
    "is_legendary": false,
    "is_mythical": false,
    "is_baby": false,
    "gender_rate": 4,
    "is_mega": false,
    "is_gmax": false,
    "is_paradox": false,
    "is_primal": false,
    "is_alternate_form": false,
    "is_sublegendary": false,
    "is_ultra_beast": false,
    "evolution_stage": 0,
    "is_fully_evolved": false
  },
  {
    "id": 695,
    "name": "heliolisk",
    "speciesName": "heliolisk",
    "types": [
      "electric",
      "normal"
    ],
    "sprite": "https://raw.githubusercontent.com/PokeAPI/sprites/master/sprites/pokemon/other/home/695.png",
    "shinySprite": "https://raw.githubusercontent.com/PokeAPI/sprites/master/sprites/pokemon/other/home/shiny/695.png",
    "femaleSprite": null,
    "femaleShinySprite": null,
    "generation": 6,
    "is_legendary": false,
    "is_mythical": false,
    "is_baby": false,
    "gender_rate": 4,
    "is_mega": false,
    "is_gmax": false,
    "is_paradox": false,
    "is_primal": false,
    "is_alternate_form": false,
    "is_sublegendary": false,
    "is_ultra_beast": false,
    "evolution_stage": 1,
    "is_fully_evolved": true
  },
  {
    "id": 696,
    "name": "tyrunt",
    "speciesName": "tyrunt",
    "types": [
      "rock",
      "dragon"
    ],
    "sprite": "https://raw.githubusercontent.com/PokeAPI/sprites/master/sprites/pokemon/other/home/696.png",
    "shinySprite": "https://raw.githubusercontent.com/PokeAPI/sprites/master/sprites/pokemon/other/home/shiny/696.png",
    "femaleSprite": null,
    "femaleShinySprite": null,
    "generation": 6,
    "is_legendary": false,
    "is_mythical": false,
    "is_baby": false,
    "gender_rate": 1,
    "is_mega": false,
    "is_gmax": false,
    "is_paradox": false,
    "is_primal": false,
    "is_alternate_form": false,
    "is_sublegendary": false,
    "is_ultra_beast": false,
    "evolution_stage": 0,
    "is_fully_evolved": false
  },
  {
    "id": 697,
    "name": "tyrantrum",
    "speciesName": "tyrantrum",
    "types": [
      "rock",
      "dragon"
    ],
    "sprite": "https://raw.githubusercontent.com/PokeAPI/sprites/master/sprites/pokemon/other/home/697.png",
    "shinySprite": "https://raw.githubusercontent.com/PokeAPI/sprites/master/sprites/pokemon/other/home/shiny/697.png",
    "femaleSprite": null,
    "femaleShinySprite": null,
    "generation": 6,
    "is_legendary": false,
    "is_mythical": false,
    "is_baby": false,
    "gender_rate": 1,
    "is_mega": false,
    "is_gmax": false,
    "is_paradox": false,
    "is_primal": false,
    "is_alternate_form": false,
    "is_sublegendary": false,
    "is_ultra_beast": false,
    "evolution_stage": 1,
    "is_fully_evolved": true
  },
  {
    "id": 698,
    "name": "amaura",
    "speciesName": "amaura",
    "types": [
      "rock",
      "ice"
    ],
    "sprite": "https://raw.githubusercontent.com/PokeAPI/sprites/master/sprites/pokemon/other/home/698.png",
    "shinySprite": "https://raw.githubusercontent.com/PokeAPI/sprites/master/sprites/pokemon/other/home/shiny/698.png",
    "femaleSprite": null,
    "femaleShinySprite": null,
    "generation": 6,
    "is_legendary": false,
    "is_mythical": false,
    "is_baby": false,
    "gender_rate": 1,
    "is_mega": false,
    "is_gmax": false,
    "is_paradox": false,
    "is_primal": false,
    "is_alternate_form": false,
    "is_sublegendary": false,
    "is_ultra_beast": false,
    "evolution_stage": 0,
    "is_fully_evolved": false
  },
  {
    "id": 699,
    "name": "aurorus",
    "speciesName": "aurorus",
    "types": [
      "rock",
      "ice"
    ],
    "sprite": "https://raw.githubusercontent.com/PokeAPI/sprites/master/sprites/pokemon/other/home/699.png",
    "shinySprite": "https://raw.githubusercontent.com/PokeAPI/sprites/master/sprites/pokemon/other/home/shiny/699.png",
    "femaleSprite": null,
    "femaleShinySprite": null,
    "generation": 6,
    "is_legendary": false,
    "is_mythical": false,
    "is_baby": false,
    "gender_rate": 1,
    "is_mega": false,
    "is_gmax": false,
    "is_paradox": false,
    "is_primal": false,
    "is_alternate_form": false,
    "is_sublegendary": false,
    "is_ultra_beast": false,
    "evolution_stage": 1,
    "is_fully_evolved": true
  },
  {
    "id": 700,
    "name": "sylveon",
    "speciesName": "sylveon",
    "types": [
      "fairy"
    ],
    "sprite": "https://raw.githubusercontent.com/PokeAPI/sprites/master/sprites/pokemon/other/home/700.png",
    "shinySprite": "https://raw.githubusercontent.com/PokeAPI/sprites/master/sprites/pokemon/other/home/shiny/700.png",
    "femaleSprite": null,
    "femaleShinySprite": null,
    "generation": 6,
    "is_legendary": false,
    "is_mythical": false,
    "is_baby": false,
    "gender_rate": 1,
    "is_mega": false,
    "is_gmax": false,
    "is_paradox": false,
    "is_primal": false,
    "is_alternate_form": false,
    "is_sublegendary": false,
    "is_ultra_beast": false,
    "evolution_stage": 1,
    "is_fully_evolved": true
  },
  {
    "id": 701,
    "name": "hawlucha",
    "speciesName": "hawlucha",
    "types": [
      "fighting",
      "flying"
    ],
    "sprite": "https://raw.githubusercontent.com/PokeAPI/sprites/master/sprites/pokemon/other/home/701.png",
    "shinySprite": "https://raw.githubusercontent.com/PokeAPI/sprites/master/sprites/pokemon/other/home/shiny/701.png",
    "femaleSprite": null,
    "femaleShinySprite": null,
    "generation": 6,
    "is_legendary": false,
    "is_mythical": false,
    "is_baby": false,
    "gender_rate": 4,
    "is_mega": false,
    "is_gmax": false,
    "is_paradox": false,
    "is_primal": false,
    "is_alternate_form": false,
    "is_sublegendary": false,
    "is_ultra_beast": false,
    "evolution_stage": 0,
    "is_fully_evolved": true
  },
  {
    "id": 702,
    "name": "dedenne",
    "speciesName": "dedenne",
    "types": [
      "electric",
      "fairy"
    ],
    "sprite": "https://raw.githubusercontent.com/PokeAPI/sprites/master/sprites/pokemon/other/home/702.png",
    "shinySprite": "https://raw.githubusercontent.com/PokeAPI/sprites/master/sprites/pokemon/other/home/shiny/702.png",
    "femaleSprite": null,
    "femaleShinySprite": null,
    "generation": 6,
    "is_legendary": false,
    "is_mythical": false,
    "is_baby": false,
    "gender_rate": 4,
    "is_mega": false,
    "is_gmax": false,
    "is_paradox": false,
    "is_primal": false,
    "is_alternate_form": false,
    "is_sublegendary": false,
    "is_ultra_beast": false,
    "evolution_stage": 0,
    "is_fully_evolved": true
  },
  {
    "id": 703,
    "name": "carbink",
    "speciesName": "carbink",
    "types": [
      "rock",
      "fairy"
    ],
    "sprite": "https://raw.githubusercontent.com/PokeAPI/sprites/master/sprites/pokemon/other/home/703.png",
    "shinySprite": "https://raw.githubusercontent.com/PokeAPI/sprites/master/sprites/pokemon/other/home/shiny/703.png",
    "femaleSprite": null,
    "femaleShinySprite": null,
    "generation": 6,
    "is_legendary": false,
    "is_mythical": false,
    "is_baby": false,
    "gender_rate": -1,
    "is_mega": false,
    "is_gmax": false,
    "is_paradox": false,
    "is_primal": false,
    "is_alternate_form": false,
    "is_sublegendary": false,
    "is_ultra_beast": false,
    "evolution_stage": 0,
    "is_fully_evolved": true
  },
  {
    "id": 704,
    "name": "goomy",
    "speciesName": "goomy",
    "types": [
      "dragon"
    ],
    "sprite": "https://raw.githubusercontent.com/PokeAPI/sprites/master/sprites/pokemon/other/home/704.png",
    "shinySprite": "https://raw.githubusercontent.com/PokeAPI/sprites/master/sprites/pokemon/other/home/shiny/704.png",
    "femaleSprite": null,
    "femaleShinySprite": null,
    "generation": 6,
    "is_legendary": false,
    "is_mythical": false,
    "is_baby": false,
    "gender_rate": 4,
    "is_mega": false,
    "is_gmax": false,
    "is_paradox": false,
    "is_primal": false,
    "is_alternate_form": false,
    "is_sublegendary": false,
    "is_ultra_beast": false,
    "evolution_stage": 0,
    "is_fully_evolved": false
  },
  {
    "id": 705,
    "name": "sliggoo",
    "speciesName": "sliggoo",
    "types": [
      "dragon"
    ],
    "sprite": "https://raw.githubusercontent.com/PokeAPI/sprites/master/sprites/pokemon/other/home/705.png",
    "shinySprite": "https://raw.githubusercontent.com/PokeAPI/sprites/master/sprites/pokemon/other/home/shiny/705.png",
    "femaleSprite": null,
    "femaleShinySprite": null,
    "generation": 6,
    "is_legendary": false,
    "is_mythical": false,
    "is_baby": false,
    "gender_rate": 4,
    "is_mega": false,
    "is_gmax": false,
    "is_paradox": false,
    "is_primal": false,
    "is_alternate_form": false,
    "is_sublegendary": false,
    "is_ultra_beast": false,
    "evolution_stage": 1,
    "is_fully_evolved": false
  },
  {
    "id": 706,
    "name": "goodra",
    "speciesName": "goodra",
    "types": [
      "dragon"
    ],
    "sprite": "https://raw.githubusercontent.com/PokeAPI/sprites/master/sprites/pokemon/other/home/706.png",
    "shinySprite": "https://raw.githubusercontent.com/PokeAPI/sprites/master/sprites/pokemon/other/home/shiny/706.png",
    "femaleSprite": null,
    "femaleShinySprite": null,
    "generation": 6,
    "is_legendary": false,
    "is_mythical": false,
    "is_baby": false,
    "gender_rate": 4,
    "is_mega": false,
    "is_gmax": false,
    "is_paradox": false,
    "is_primal": false,
    "is_alternate_form": false,
    "is_sublegendary": false,
    "is_ultra_beast": false,
    "evolution_stage": 2,
    "is_fully_evolved": true
  },
  {
    "id": 707,
    "name": "klefki",
    "speciesName": "klefki",
    "types": [
      "steel",
      "fairy"
    ],
    "sprite": "https://raw.githubusercontent.com/PokeAPI/sprites/master/sprites/pokemon/other/home/707.png",
    "shinySprite": "https://raw.githubusercontent.com/PokeAPI/sprites/master/sprites/pokemon/other/home/shiny/707.png",
    "femaleSprite": null,
    "femaleShinySprite": null,
    "generation": 6,
    "is_legendary": false,
    "is_mythical": false,
    "is_baby": false,
    "gender_rate": 4,
    "is_mega": false,
    "is_gmax": false,
    "is_paradox": false,
    "is_primal": false,
    "is_alternate_form": false,
    "is_sublegendary": false,
    "is_ultra_beast": false,
    "evolution_stage": 0,
    "is_fully_evolved": true
  },
  {
    "id": 708,
    "name": "phantump",
    "speciesName": "phantump",
    "types": [
      "ghost",
      "grass"
    ],
    "sprite": "https://raw.githubusercontent.com/PokeAPI/sprites/master/sprites/pokemon/other/home/708.png",
    "shinySprite": "https://raw.githubusercontent.com/PokeAPI/sprites/master/sprites/pokemon/other/home/shiny/708.png",
    "femaleSprite": null,
    "femaleShinySprite": null,
    "generation": 6,
    "is_legendary": false,
    "is_mythical": false,
    "is_baby": false,
    "gender_rate": 4,
    "is_mega": false,
    "is_gmax": false,
    "is_paradox": false,
    "is_primal": false,
    "is_alternate_form": false,
    "is_sublegendary": false,
    "is_ultra_beast": false,
    "evolution_stage": 0,
    "is_fully_evolved": false
  },
  {
    "id": 709,
    "name": "trevenant",
    "speciesName": "trevenant",
    "types": [
      "ghost",
      "grass"
    ],
    "sprite": "https://raw.githubusercontent.com/PokeAPI/sprites/master/sprites/pokemon/other/home/709.png",
    "shinySprite": "https://raw.githubusercontent.com/PokeAPI/sprites/master/sprites/pokemon/other/home/shiny/709.png",
    "femaleSprite": null,
    "femaleShinySprite": null,
    "generation": 6,
    "is_legendary": false,
    "is_mythical": false,
    "is_baby": false,
    "gender_rate": 4,
    "is_mega": false,
    "is_gmax": false,
    "is_paradox": false,
    "is_primal": false,
    "is_alternate_form": false,
    "is_sublegendary": false,
    "is_ultra_beast": false,
    "evolution_stage": 1,
    "is_fully_evolved": true
  },
  {
    "id": 710,
    "name": "pumpkaboo-average",
    "speciesName": "pumpkaboo",
    "types": [
      "ghost",
      "grass"
    ],
    "sprite": "https://raw.githubusercontent.com/PokeAPI/sprites/master/sprites/pokemon/other/home/710.png",
    "shinySprite": "https://raw.githubusercontent.com/PokeAPI/sprites/master/sprites/pokemon/other/home/shiny/710.png",
    "femaleSprite": null,
    "femaleShinySprite": null,
    "generation": 6,
    "is_legendary": false,
    "is_mythical": false,
    "is_baby": false,
    "gender_rate": 4,
    "is_mega": false,
    "is_gmax": false,
    "is_paradox": false,
    "is_primal": false,
    "is_alternate_form": true,
    "is_sublegendary": false,
    "is_ultra_beast": false,
    "evolution_stage": 0,
    "is_fully_evolved": false
  },
  {
    "id": 711,
    "name": "gourgeist-average",
    "speciesName": "gourgeist",
    "types": [
      "ghost",
      "grass"
    ],
    "sprite": "https://raw.githubusercontent.com/PokeAPI/sprites/master/sprites/pokemon/other/home/711.png",
    "shinySprite": "https://raw.githubusercontent.com/PokeAPI/sprites/master/sprites/pokemon/other/home/shiny/711.png",
    "femaleSprite": null,
    "femaleShinySprite": null,
    "generation": 6,
    "is_legendary": false,
    "is_mythical": false,
    "is_baby": false,
    "gender_rate": 4,
    "is_mega": false,
    "is_gmax": false,
    "is_paradox": false,
    "is_primal": false,
    "is_alternate_form": true,
    "is_sublegendary": false,
    "is_ultra_beast": false,
    "evolution_stage": 1,
    "is_fully_evolved": true
  },
  {
    "id": 712,
    "name": "bergmite",
    "speciesName": "bergmite",
    "types": [
      "ice"
    ],
    "sprite": "https://raw.githubusercontent.com/PokeAPI/sprites/master/sprites/pokemon/other/home/712.png",
    "shinySprite": "https://raw.githubusercontent.com/PokeAPI/sprites/master/sprites/pokemon/other/home/shiny/712.png",
    "femaleSprite": null,
    "femaleShinySprite": null,
    "generation": 6,
    "is_legendary": false,
    "is_mythical": false,
    "is_baby": false,
    "gender_rate": 4,
    "is_mega": false,
    "is_gmax": false,
    "is_paradox": false,
    "is_primal": false,
    "is_alternate_form": false,
    "is_sublegendary": false,
    "is_ultra_beast": false,
    "evolution_stage": 0,
    "is_fully_evolved": false
  },
  {
    "id": 713,
    "name": "avalugg",
    "speciesName": "avalugg",
    "types": [
      "ice"
    ],
    "sprite": "https://raw.githubusercontent.com/PokeAPI/sprites/master/sprites/pokemon/other/home/713.png",
    "shinySprite": "https://raw.githubusercontent.com/PokeAPI/sprites/master/sprites/pokemon/other/home/shiny/713.png",
    "femaleSprite": null,
    "femaleShinySprite": null,
    "generation": 6,
    "is_legendary": false,
    "is_mythical": false,
    "is_baby": false,
    "gender_rate": 4,
    "is_mega": false,
    "is_gmax": false,
    "is_paradox": false,
    "is_primal": false,
    "is_alternate_form": false,
    "is_sublegendary": false,
    "is_ultra_beast": false,
    "evolution_stage": 1,
    "is_fully_evolved": true
  },
  {
    "id": 714,
    "name": "noibat",
    "speciesName": "noibat",
    "types": [
      "flying",
      "dragon"
    ],
    "sprite": "https://raw.githubusercontent.com/PokeAPI/sprites/master/sprites/pokemon/other/home/714.png",
    "shinySprite": "https://raw.githubusercontent.com/PokeAPI/sprites/master/sprites/pokemon/other/home/shiny/714.png",
    "femaleSprite": null,
    "femaleShinySprite": null,
    "generation": 6,
    "is_legendary": false,
    "is_mythical": false,
    "is_baby": false,
    "gender_rate": 4,
    "is_mega": false,
    "is_gmax": false,
    "is_paradox": false,
    "is_primal": false,
    "is_alternate_form": false,
    "is_sublegendary": false,
    "is_ultra_beast": false,
    "evolution_stage": 0,
    "is_fully_evolved": false
  },
  {
    "id": 715,
    "name": "noivern",
    "speciesName": "noivern",
    "types": [
      "flying",
      "dragon"
    ],
    "sprite": "https://raw.githubusercontent.com/PokeAPI/sprites/master/sprites/pokemon/other/home/715.png",
    "shinySprite": "https://raw.githubusercontent.com/PokeAPI/sprites/master/sprites/pokemon/other/home/shiny/715.png",
    "femaleSprite": null,
    "femaleShinySprite": null,
    "generation": 6,
    "is_legendary": false,
    "is_mythical": false,
    "is_baby": false,
    "gender_rate": 4,
    "is_mega": false,
    "is_gmax": false,
    "is_paradox": false,
    "is_primal": false,
    "is_alternate_form": false,
    "is_sublegendary": false,
    "is_ultra_beast": false,
    "evolution_stage": 1,
    "is_fully_evolved": true
  },
  {
    "id": 716,
    "name": "xerneas",
    "speciesName": "xerneas",
    "types": [
      "fairy"
    ],
    "sprite": "https://raw.githubusercontent.com/PokeAPI/sprites/master/sprites/pokemon/other/home/716.png",
    "shinySprite": "https://raw.githubusercontent.com/PokeAPI/sprites/master/sprites/pokemon/other/home/shiny/716.png",
    "femaleSprite": null,
    "femaleShinySprite": null,
    "generation": 6,
    "is_legendary": true,
    "is_mythical": false,
    "is_baby": false,
    "gender_rate": -1,
    "is_mega": false,
    "is_gmax": false,
    "is_paradox": false,
    "is_primal": false,
    "is_alternate_form": false,
    "is_sublegendary": false,
    "is_ultra_beast": false,
    "evolution_stage": 0,
    "is_fully_evolved": true
  },
  {
    "id": 717,
    "name": "yveltal",
    "speciesName": "yveltal",
    "types": [
      "dark",
      "flying"
    ],
    "sprite": "https://raw.githubusercontent.com/PokeAPI/sprites/master/sprites/pokemon/other/home/717.png",
    "shinySprite": "https://raw.githubusercontent.com/PokeAPI/sprites/master/sprites/pokemon/other/home/shiny/717.png",
    "femaleSprite": null,
    "femaleShinySprite": null,
    "generation": 6,
    "is_legendary": true,
    "is_mythical": false,
    "is_baby": false,
    "gender_rate": -1,
    "is_mega": false,
    "is_gmax": false,
    "is_paradox": false,
    "is_primal": false,
    "is_alternate_form": false,
    "is_sublegendary": false,
    "is_ultra_beast": false,
    "evolution_stage": 0,
    "is_fully_evolved": true
  },
  {
    "id": 718,
    "name": "zygarde-50",
    "speciesName": "zygarde",
    "types": [
      "dragon",
      "ground"
    ],
    "sprite": "https://raw.githubusercontent.com/PokeAPI/sprites/master/sprites/pokemon/other/home/718.png",
    "shinySprite": "https://raw.githubusercontent.com/PokeAPI/sprites/master/sprites/pokemon/other/home/shiny/718.png",
    "femaleSprite": null,
    "femaleShinySprite": null,
    "generation": 6,
    "is_legendary": true,
    "is_mythical": false,
    "is_baby": false,
    "gender_rate": -1,
    "is_mega": false,
    "is_gmax": false,
    "is_paradox": false,
    "is_primal": false,
    "is_alternate_form": true,
    "is_sublegendary": false,
    "is_ultra_beast": false,
    "evolution_stage": 0,
    "is_fully_evolved": true
  },
  {
    "id": 719,
    "name": "diancie",
    "speciesName": "diancie",
    "types": [
      "rock",
      "fairy"
    ],
    "sprite": "https://raw.githubusercontent.com/PokeAPI/sprites/master/sprites/pokemon/other/home/719.png",
    "shinySprite": "https://raw.githubusercontent.com/PokeAPI/sprites/master/sprites/pokemon/other/home/shiny/719.png",
    "femaleSprite": null,
    "femaleShinySprite": null,
    "generation": 6,
    "is_legendary": false,
    "is_mythical": true,
    "is_baby": false,
    "gender_rate": -1,
    "is_mega": false,
    "is_gmax": false,
    "is_paradox": false,
    "is_primal": false,
    "is_alternate_form": false,
    "is_sublegendary": false,
    "is_ultra_beast": false,
    "evolution_stage": 0,
    "is_fully_evolved": true
  },
  {
    "id": 720,
    "name": "hoopa",
    "speciesName": "hoopa",
    "types": [
      "psychic",
      "ghost"
    ],
    "sprite": "https://raw.githubusercontent.com/PokeAPI/sprites/master/sprites/pokemon/other/home/720.png",
    "shinySprite": "https://raw.githubusercontent.com/PokeAPI/sprites/master/sprites/pokemon/other/home/shiny/720.png",
    "femaleSprite": null,
    "femaleShinySprite": null,
    "generation": 6,
    "is_legendary": false,
    "is_mythical": true,
    "is_baby": false,
    "gender_rate": -1,
    "is_mega": false,
    "is_gmax": false,
    "is_paradox": false,
    "is_primal": false,
    "is_alternate_form": false,
    "is_sublegendary": false,
    "is_ultra_beast": false,
    "evolution_stage": 0,
    "is_fully_evolved": true
  },
  {
    "id": 721,
    "name": "volcanion",
    "speciesName": "volcanion",
    "types": [
      "fire",
      "water"
    ],
    "sprite": "https://raw.githubusercontent.com/PokeAPI/sprites/master/sprites/pokemon/other/home/721.png",
    "shinySprite": "https://raw.githubusercontent.com/PokeAPI/sprites/master/sprites/pokemon/other/home/shiny/721.png",
    "femaleSprite": null,
    "femaleShinySprite": null,
    "generation": 6,
    "is_legendary": false,
    "is_mythical": true,
    "is_baby": false,
    "gender_rate": -1,
    "is_mega": false,
    "is_gmax": false,
    "is_paradox": false,
    "is_primal": false,
    "is_alternate_form": false,
    "is_sublegendary": false,
    "is_ultra_beast": false,
    "evolution_stage": 0,
    "is_fully_evolved": true
  },
  {
    "id": 10025,
    "name": "meowstic-female",
    "speciesName": "meowstic",
    "types": [
      "psychic"
    ],
    "sprite": "https://raw.githubusercontent.com/PokeAPI/sprites/master/sprites/pokemon/other/home/10025.png",
    "shinySprite": "https://raw.githubusercontent.com/PokeAPI/sprites/master/sprites/pokemon/other/home/shiny/10025.png",
    "femaleSprite": null,
    "femaleShinySprite": null,
    "generation": 6,
    "is_legendary": false,
    "is_mythical": false,
    "is_baby": false,
    "gender_rate": 4,
    "is_mega": false,
    "is_gmax": false,
    "is_paradox": false,
    "is_primal": false,
    "is_alternate_form": true,
    "is_sublegendary": false,
    "is_ultra_beast": false,
    "evolution_stage": 1,
    "is_fully_evolved": true
  },
  {
    "id": 10026,
    "name": "aegislash-blade",
    "speciesName": "aegislash",
    "types": [
      "steel",
      "ghost"
    ],
    "sprite": "https://raw.githubusercontent.com/PokeAPI/sprites/master/sprites/pokemon/other/home/10026.png",
    "shinySprite": "https://raw.githubusercontent.com/PokeAPI/sprites/master/sprites/pokemon/other/home/shiny/10026.png",
    "femaleSprite": null,
    "femaleShinySprite": null,
    "generation": 6,
    "is_legendary": false,
    "is_mythical": false,
    "is_baby": false,
    "gender_rate": 4,
    "is_mega": false,
    "is_gmax": false,
    "is_paradox": false,
    "is_primal": false,
    "is_alternate_form": true,
    "is_sublegendary": false,
    "is_ultra_beast": false,
    "evolution_stage": 2,
    "is_fully_evolved": true
  },
  {
    "id": 10027,
    "name": "pumpkaboo-small",
    "speciesName": "pumpkaboo",
    "types": [
      "ghost",
      "grass"
    ],
    "sprite": "https://raw.githubusercontent.com/PokeAPI/sprites/master/sprites/pokemon/other/home/10027.png",
    "shinySprite": "https://raw.githubusercontent.com/PokeAPI/sprites/master/sprites/pokemon/other/home/shiny/10027.png",
    "femaleSprite": null,
    "femaleShinySprite": null,
    "generation": 6,
    "is_legendary": false,
    "is_mythical": false,
    "is_baby": false,
    "gender_rate": 4,
    "is_mega": false,
    "is_gmax": false,
    "is_paradox": false,
    "is_primal": false,
    "is_alternate_form": true,
    "is_sublegendary": false,
    "is_ultra_beast": false,
    "evolution_stage": 0,
    "is_fully_evolved": false
  },
  {
    "id": 10028,
    "name": "pumpkaboo-large",
    "speciesName": "pumpkaboo",
    "types": [
      "ghost",
      "grass"
    ],
    "sprite": "https://raw.githubusercontent.com/PokeAPI/sprites/master/sprites/pokemon/other/home/10028.png",
    "shinySprite": "https://raw.githubusercontent.com/PokeAPI/sprites/master/sprites/pokemon/other/home/shiny/10028.png",
    "femaleSprite": null,
    "femaleShinySprite": null,
    "generation": 6,
    "is_legendary": false,
    "is_mythical": false,
    "is_baby": false,
    "gender_rate": 4,
    "is_mega": false,
    "is_gmax": false,
    "is_paradox": false,
    "is_primal": false,
    "is_alternate_form": true,
    "is_sublegendary": false,
    "is_ultra_beast": false,
    "evolution_stage": 0,
    "is_fully_evolved": false
  },
  {
    "id": 10029,
    "name": "pumpkaboo-super",
    "speciesName": "pumpkaboo",
    "types": [
      "ghost",
      "grass"
    ],
    "sprite": "https://raw.githubusercontent.com/PokeAPI/sprites/master/sprites/pokemon/other/home/10029.png",
    "shinySprite": "https://raw.githubusercontent.com/PokeAPI/sprites/master/sprites/pokemon/other/home/shiny/10029.png",
    "femaleSprite": null,
    "femaleShinySprite": null,
    "generation": 6,
    "is_legendary": false,
    "is_mythical": false,
    "is_baby": false,
    "gender_rate": 4,
    "is_mega": false,
    "is_gmax": false,
    "is_paradox": false,
    "is_primal": false,
    "is_alternate_form": true,
    "is_sublegendary": false,
    "is_ultra_beast": false,
    "evolution_stage": 0,
    "is_fully_evolved": false
  },
  {
    "id": 10030,
    "name": "gourgeist-small",
    "speciesName": "gourgeist",
    "types": [
      "ghost",
      "grass"
    ],
    "sprite": "https://raw.githubusercontent.com/PokeAPI/sprites/master/sprites/pokemon/other/home/10030.png",
    "shinySprite": "https://raw.githubusercontent.com/PokeAPI/sprites/master/sprites/pokemon/other/home/shiny/10030.png",
    "femaleSprite": null,
    "femaleShinySprite": null,
    "generation": 6,
    "is_legendary": false,
    "is_mythical": false,
    "is_baby": false,
    "gender_rate": 4,
    "is_mega": false,
    "is_gmax": false,
    "is_paradox": false,
    "is_primal": false,
    "is_alternate_form": true,
    "is_sublegendary": false,
    "is_ultra_beast": false,
    "evolution_stage": 1,
    "is_fully_evolved": true
  },
  {
    "id": 10031,
    "name": "gourgeist-large",
    "speciesName": "gourgeist",
    "types": [
      "ghost",
      "grass"
    ],
    "sprite": "https://raw.githubusercontent.com/PokeAPI/sprites/master/sprites/pokemon/other/home/10031.png",
    "shinySprite": "https://raw.githubusercontent.com/PokeAPI/sprites/master/sprites/pokemon/other/home/shiny/10031.png",
    "femaleSprite": null,
    "femaleShinySprite": null,
    "generation": 6,
    "is_legendary": false,
    "is_mythical": false,
    "is_baby": false,
    "gender_rate": 4,
    "is_mega": false,
    "is_gmax": false,
    "is_paradox": false,
    "is_primal": false,
    "is_alternate_form": true,
    "is_sublegendary": false,
    "is_ultra_beast": false,
    "evolution_stage": 1,
    "is_fully_evolved": true
  },
  {
    "id": 10032,
    "name": "gourgeist-super",
    "speciesName": "gourgeist",
    "types": [
      "ghost",
      "grass"
    ],
    "sprite": "https://raw.githubusercontent.com/PokeAPI/sprites/master/sprites/pokemon/other/home/10032.png",
    "shinySprite": "https://raw.githubusercontent.com/PokeAPI/sprites/master/sprites/pokemon/other/home/shiny/10032.png",
    "femaleSprite": null,
    "femaleShinySprite": null,
    "generation": 6,
    "is_legendary": false,
    "is_mythical": false,
    "is_baby": false,
    "gender_rate": 4,
    "is_mega": false,
    "is_gmax": false,
    "is_paradox": false,
    "is_primal": false,
    "is_alternate_form": true,
    "is_sublegendary": false,
    "is_ultra_beast": false,
    "evolution_stage": 1,
    "is_fully_evolved": true
  },
  {
    "id": 10061,
    "name": "floette-eternal",
    "speciesName": "floette",
    "types": [
      "fairy"
    ],
    "sprite": "https://raw.githubusercontent.com/PokeAPI/sprites/master/sprites/pokemon/other/official-artwork/10061.png",
    "shinySprite": "https://raw.githubusercontent.com/PokeAPI/sprites/master/sprites/pokemon/other/official-artwork/shiny/10061.png",
    "femaleSprite": null,
    "femaleShinySprite": null,
    "generation": 6,
    "is_legendary": false,
    "is_mythical": false,
    "is_baby": false,
    "gender_rate": 8,
    "is_mega": false,
    "is_gmax": false,
    "is_paradox": false,
    "is_primal": false,
    "is_alternate_form": true,
    "is_sublegendary": false,
    "is_ultra_beast": false,
    "evolution_stage": 1,
    "is_fully_evolved": false
  },
  {
    "id": 10075,
    "name": "diancie-mega",
    "speciesName": "diancie",
    "types": [
      "rock",
      "fairy"
    ],
    "sprite": "https://raw.githubusercontent.com/PokeAPI/sprites/master/sprites/pokemon/other/home/10075.png",
    "shinySprite": "https://raw.githubusercontent.com/PokeAPI/sprites/master/sprites/pokemon/other/home/shiny/10075.png",
    "femaleSprite": null,
    "femaleShinySprite": null,
    "generation": 6,
    "is_legendary": false,
    "is_mythical": true,
    "is_baby": false,
    "gender_rate": -1,
    "is_mega": true,
    "is_gmax": false,
    "is_paradox": false,
    "is_primal": false,
    "is_alternate_form": false,
    "is_sublegendary": false,
    "is_ultra_beast": false,
    "evolution_stage": 0,
    "is_fully_evolved": true
  },
  {
    "id": 10086,
    "name": "hoopa-unbound",
    "speciesName": "hoopa",
    "types": [
      "psychic",
      "dark"
    ],
    "sprite": "https://raw.githubusercontent.com/PokeAPI/sprites/master/sprites/pokemon/other/home/10086.png",
    "shinySprite": "https://raw.githubusercontent.com/PokeAPI/sprites/master/sprites/pokemon/other/home/shiny/10086.png",
    "femaleSprite": null,
    "femaleShinySprite": null,
    "generation": 6,
    "is_legendary": false,
    "is_mythical": true,
    "is_baby": false,
    "gender_rate": -1,
    "is_mega": false,
    "is_gmax": false,
    "is_paradox": false,
    "is_primal": false,
    "is_alternate_form": true,
    "is_sublegendary": false,
    "is_ultra_beast": false,
    "evolution_stage": 0,
    "is_fully_evolved": true
  },
  {
    "id": 10116,
    "name": "greninja-battle-bond",
    "speciesName": "greninja",
    "types": [
      "water",
      "dark"
    ],
    "sprite": "https://raw.githubusercontent.com/PokeAPI/sprites/master/sprites/pokemon/other/home/10116.png",
    "shinySprite": "https://raw.githubusercontent.com/PokeAPI/sprites/master/sprites/pokemon/other/home/shiny/10116.png",
    "femaleSprite": null,
    "femaleShinySprite": null,
    "generation": 6,
    "is_legendary": false,
    "is_mythical": false,
    "is_baby": false,
    "gender_rate": 1,
    "is_mega": false,
    "is_gmax": false,
    "is_paradox": false,
    "is_primal": false,
    "is_alternate_form": true,
    "is_sublegendary": false,
    "is_ultra_beast": false,
    "evolution_stage": 2,
    "is_fully_evolved": true
  },
  {
    "id": 10117,
    "name": "greninja-ash",
    "speciesName": "greninja",
    "types": [
      "water",
      "dark"
    ],
    "sprite": "https://raw.githubusercontent.com/PokeAPI/sprites/master/sprites/pokemon/other/home/10117.png",
    "shinySprite": "https://raw.githubusercontent.com/PokeAPI/sprites/master/sprites/pokemon/other/home/shiny/10117.png",
    "femaleSprite": null,
    "femaleShinySprite": null,
    "generation": 6,
    "is_legendary": false,
    "is_mythical": false,
    "is_baby": false,
    "gender_rate": 1,
    "is_mega": false,
    "is_gmax": false,
    "is_paradox": false,
    "is_primal": false,
    "is_alternate_form": true,
    "is_sublegendary": false,
    "is_ultra_beast": false,
    "evolution_stage": 2,
    "is_fully_evolved": true
  },
  {
    "id": 10118,
    "name": "zygarde-10-power-construct",
    "speciesName": "zygarde",
    "types": [
      "dragon",
      "ground"
    ],
    "sprite": "https://raw.githubusercontent.com/PokeAPI/sprites/master/sprites/pokemon/other/home/10118.png",
    "shinySprite": "https://raw.githubusercontent.com/PokeAPI/sprites/master/sprites/pokemon/other/home/shiny/10118.png",
    "femaleSprite": null,
    "femaleShinySprite": null,
    "generation": 6,
    "is_legendary": true,
    "is_mythical": false,
    "is_baby": false,
    "gender_rate": -1,
    "is_mega": false,
    "is_gmax": false,
    "is_paradox": false,
    "is_primal": false,
    "is_alternate_form": true,
    "is_sublegendary": false,
    "is_ultra_beast": false,
    "evolution_stage": 0,
    "is_fully_evolved": true
  },
  {
    "id": 10119,
    "name": "zygarde-50-power-construct",
    "speciesName": "zygarde",
    "types": [
      "dragon",
      "ground"
    ],
    "sprite": "https://raw.githubusercontent.com/PokeAPI/sprites/master/sprites/pokemon/other/home/10119.png",
    "shinySprite": "https://raw.githubusercontent.com/PokeAPI/sprites/master/sprites/pokemon/other/home/shiny/10119.png",
    "femaleSprite": null,
    "femaleShinySprite": null,
    "generation": 6,
    "is_legendary": true,
    "is_mythical": false,
    "is_baby": false,
    "gender_rate": -1,
    "is_mega": false,
    "is_gmax": false,
    "is_paradox": false,
    "is_primal": false,
    "is_alternate_form": true,
    "is_sublegendary": false,
    "is_ultra_beast": false,
    "evolution_stage": 0,
    "is_fully_evolved": true
  },
  {
    "id": 10120,
    "name": "zygarde-complete",
    "speciesName": "zygarde",
    "types": [
      "dragon",
      "ground"
    ],
    "sprite": "https://raw.githubusercontent.com/PokeAPI/sprites/master/sprites/pokemon/other/home/10120.png",
    "shinySprite": "https://raw.githubusercontent.com/PokeAPI/sprites/master/sprites/pokemon/other/home/shiny/10120.png",
    "femaleSprite": null,
    "femaleShinySprite": null,
    "generation": 6,
    "is_legendary": true,
    "is_mythical": false,
    "is_baby": false,
    "gender_rate": -1,
    "is_mega": false,
    "is_gmax": false,
    "is_paradox": false,
    "is_primal": false,
    "is_alternate_form": true,
    "is_sublegendary": false,
    "is_ultra_beast": false,
    "evolution_stage": 0,
    "is_fully_evolved": true
  },
  {
    "id": 10181,
    "name": "zygarde-10",
    "speciesName": "zygarde",
    "types": [
      "dragon",
      "ground"
    ],
    "sprite": "https://raw.githubusercontent.com/PokeAPI/sprites/master/sprites/pokemon/other/home/10181.png",
    "shinySprite": "https://raw.githubusercontent.com/PokeAPI/sprites/master/sprites/pokemon/other/home/shiny/10181.png",
    "femaleSprite": null,
    "femaleShinySprite": null,
    "generation": 6,
    "is_legendary": true,
    "is_mythical": false,
    "is_baby": false,
    "gender_rate": -1,
    "is_mega": false,
    "is_gmax": false,
    "is_paradox": false,
    "is_primal": false,
    "is_alternate_form": true,
    "is_sublegendary": false,
    "is_ultra_beast": false,
    "evolution_stage": 0,
    "is_fully_evolved": true
  },
  {
    "id": 10241,
    "name": "sliggoo-hisui",
    "speciesName": "sliggoo",
    "types": [
      "steel",
      "dragon"
    ],
    "sprite": "https://raw.githubusercontent.com/PokeAPI/sprites/master/sprites/pokemon/other/home/10241.png",
    "shinySprite": "https://raw.githubusercontent.com/PokeAPI/sprites/master/sprites/pokemon/other/home/shiny/10241.png",
    "femaleSprite": null,
    "femaleShinySprite": null,
    "generation": 6,
    "is_legendary": false,
    "is_mythical": false,
    "is_baby": false,
    "gender_rate": 4,
    "is_mega": false,
    "is_gmax": false,
    "is_paradox": false,
    "is_primal": false,
    "is_alternate_form": true,
    "is_sublegendary": false,
    "is_ultra_beast": false,
    "evolution_stage": 1,
    "is_fully_evolved": false
  },
  {
    "id": 10242,
    "name": "goodra-hisui",
    "speciesName": "goodra",
    "types": [
      "steel",
      "dragon"
    ],
    "sprite": "https://raw.githubusercontent.com/PokeAPI/sprites/master/sprites/pokemon/other/home/10242.png",
    "shinySprite": "https://raw.githubusercontent.com/PokeAPI/sprites/master/sprites/pokemon/other/home/shiny/10242.png",
    "femaleSprite": null,
    "femaleShinySprite": null,
    "generation": 6,
    "is_legendary": false,
    "is_mythical": false,
    "is_baby": false,
    "gender_rate": 4,
    "is_mega": false,
    "is_gmax": false,
    "is_paradox": false,
    "is_primal": false,
    "is_alternate_form": true,
    "is_sublegendary": false,
    "is_ultra_beast": false,
    "evolution_stage": 2,
    "is_fully_evolved": true
  },
  {
    "id": 10243,
    "name": "avalugg-hisui",
    "speciesName": "avalugg",
    "types": [
      "ice",
      "rock"
    ],
    "sprite": "https://raw.githubusercontent.com/PokeAPI/sprites/master/sprites/pokemon/other/home/10243.png",
    "shinySprite": "https://raw.githubusercontent.com/PokeAPI/sprites/master/sprites/pokemon/other/home/shiny/10243.png",
    "femaleSprite": null,
    "femaleShinySprite": null,
    "generation": 6,
    "is_legendary": false,
    "is_mythical": false,
    "is_baby": false,
    "gender_rate": 4,
    "is_mega": false,
    "is_gmax": false,
    "is_paradox": false,
    "is_primal": false,
    "is_alternate_form": true,
    "is_sublegendary": false,
    "is_ultra_beast": false,
    "evolution_stage": 1,
    "is_fully_evolved": true
  }
]